requests_threads.py
requests_threads-0.1.0.dist-info/DESCRIPTION.rst
requests_threads-0.1.0.dist-info/METADATA
requests_threads-0.1.0.dist-info/RECORD
requests_threads-0.1.0.dist-info/WHEEL
requests_threads-0.1.0.dist-info/metadata.json
requests_threads-0.1.0.dist-info/top_level.txt
