Metadata-Version: 2.0
Name: requests-threads
Version: 0.1.0
Summary: A Requests session that returns awaitable Twisted Deferreds instead of response objects.
Home-page: https://github.com/requests/requests/requests-threads
Author: Kenneth Reitz
Author-email: me@kennethreitz.org
License: ISC
Platform: UNKNOWN
Classifier: License :: OSI Approved :: MIT License
Classifier: Programming Language :: Python
Classifier: Programming Language :: Python :: 2.6
Classifier: Programming Language :: Python :: 2.7
Classifier: Programming Language :: Python :: 3
Classifier: Programming Language :: Python :: 3.3
Classifier: Programming Language :: Python :: 3.4
Classifier: Programming Language :: Python :: 3.5
Classifier: Programming Language :: Python :: 3.6
Classifier: Programming Language :: Python :: Implementation :: CPython
Classifier: Programming Language :: Python :: Implementation :: PyPy
Requires-Dist: requests
Requires-Dist: twisted
